{ "height":10,
 "infinite":false,
 "layers":[
        {
         "data":[0, 0, 0, 0, 0, 0, 0, 0, 0, 0, 0, 0, 0, 0, 0, 0, 0, 0, 0, 0, 0, 0, 0, 0, 0, 0, 0, 0, 0, 0, 0, 0, 0, 0, 0, 0, 0, 0, 0, 0, 0, 0, 0, 0, 0, 0, 0, 0, 0, 0, 0, 0, 0, 0, 0, 0, 0, 0, 0, 0, 0, 0, 0, 0, 0, 0, 0, 0, 0, 0, 0, 0, 0, 0, 0, 0, 0, 0, 0, 0, 0, 0, 0, 0, 0, 0, 0, 0, 0, 0, 0, 0, 0, 0, 0, 0, 23, 20, 20, 20, 21, 0, 0, 0, 0, 0, 0, 0, 0, 0, 0, 0, 0, 0, 0, 0, 0, 0, 0, 0, 0, 0, 0, 0, 0, 23, 40, 37, 37, 37, 38, 0, 0, 0, 0, 0, 0, 0, 0, 0, 0, 0, 0, 0, 0, 0, 0, 0, 0, 0, 20, 20, 20, 20, 20, 40, 37, 37, 37, 37, 38, 0, 0, 0, 0, 0, 0, 0, 0, 0, 0, 0, 0, 0, 0, 0, 0, 0, 0, 0, 37, 37, 37, 37, 37, 37, 37, 37, 37, 37, 38, 0, 0, 0, 0, 0, 0, 0, 0, 0, 0, 0, 0, 0, 0, 0, 0, 0, 0, 0, 37, 37, 37, 37, 37, 37, 37, 37, 37, 37, 38, 0, 0, 0, 0, 0, 0, 0, 0, 0, 0, 0, 0, 0, 0, 0, 0, 0, 0, 0, 37, 37, 37, 37, 37, 37, 37, 37, 37, 37, 38, 0, 0, 0, 0, 0, 0, 0, 0, 0, 0, 0, 0, 0, 0, 0, 0, 0, 0, 0, 37, 37, 37, 37, 37, 37, 37, 37, 37, 37, 38, 0, 0, 0, 0, 0, 0, 0, 0, 0, 0, 0, 0, 0, 0, 0, 0, 0, 0, 0],
         "height":10,
         "id":3,
         "name":"layer_1",
         "opacity":1,
         "type":"tilelayer",
         "visible":true,
         "width":30,
         "x":0,
         "y":0
        }, 
        {
         "draworder":"topdown",
         "id":7,
         "name":"layer_collision",
         "objects":[
                {
                 "height":0,
                 "id":3,
                 "name":"",
                 "polygon":[
                        {
                         "x":0,
                         "y":0
                        }, 
                        {
                         "x":354.666666666667,
                         "y":-2.66666666666669
                        }, 
                        {
                         "x":362.666666666667,
                         "y":-4
                        }, 
                        {
                         "x":376,
                         "y":-40
                        }, 
                        {
                         "x":434.666666666667,
                         "y":-78.6666666666667
                        }, 
                        {
                         "x":449.333333333333,
                         "y":-113.333333333333
                        }, 
                        {
                         "x":492,
                         "y":-145.333333333333
                        }, 
                        {
                         "x":786.666666666667,
                         "y":-146.666666666667
                        }, 
                        {
                         "x":781.333333333333,
                         "y":353.333333333333
                        }, 
                        {
                         "x":1.33333333333333,
                         "y":354.666666666667
                        }],
                 "rotation":0,
                 "type":"",
                 "visible":true,
                 "width":0,
                 "x":-1.33333333333333,
                 "y":365.333333333333
                }],
         "opacity":1,
         "type":"objectgroup",
         "visible":true,
         "x":0,
         "y":0
        }],
 "nextlayerid":8,
 "nextobjectid":4,
 "orientation":"orthogonal",
 "renderorder":"right-down",
 "tiledversion":"2018.05.24",
 "tileheight":72,
 "tilesets":[
        {
         "columns":17,
         "firstgid":1,
         "image":"..\/..\/..\/..\/..\/..\/projects\/tiled_project\/final\/forest.png",
         "imageheight":720,
         "imagewidth":1280,
         "margin":0,
         "name":"forest",
         "spacing":0,
         "tilecount":170,
         "tileheight":72,
         "tiles":[
                {
                 "id":18,
                 "objectgroup":
                    {
                     "draworder":"index",
                     "name":"",
                     "objects":[
                            {
                             "height":0,
                             "id":5,
                             "name":"",
                             "polygon":[
                                    {
                                     "x":0,
                                     "y":0
                                    }, 
                                    {
                                     "x":69.8182,
                                     "y":0.363636
                                    }, 
                                    {
                                     "x":69.8182,
                                     "y":70
                                    }, 
                                    {
                                     "x":12.5455,
                                     "y":70.3636
                                    }, 
                                    {
                                     "x":10.1818,
                                     "y":56
                                    }, 
                                    {
                                     "x":17.8182,
                                     "y":49.2727
                                    }, 
                                    {
                                     "x":7.09091,
                                     "y":40.5455
                                    }, 
                                    {
                                     "x":2.18182,
                                     "y":23.8182
                                    }, 
                                    {
                                     "x":8.72727,
                                     "y":13.4545
                                    }],
                             "rotation":0,
                             "type":"",
                             "visible":true,
                             "width":0,
                             "x":2,
                             "y":1.81818
                            }],
                     "opacity":1,
                     "type":"objectgroup",
                     "visible":true,
                     "x":0,
                     "y":0
                    },
                 "properties":[
                        {
                         "name":"collides",
                         "type":"string",
                         "value":"true"
                        }]
                }, 
                {
                 "id":19,
                 "objectgroup":
                    {
                     "draworder":"index",
                     "name":"",
                     "objects":[
                            {
                             "height":69.6364,
                             "id":1,
                             "name":"",
                             "rotation":0,
                             "type":"",
                             "visible":true,
                             "width":72.1818,
                             "x":0,
                             "y":2.54545
                            }],
                     "opacity":1,
                     "type":"objectgroup",
                     "visible":true,
                     "x":0,
                     "y":0
                    },
                 "properties":[
                        {
                         "name":"collides",
                         "type":"string",
                         "value":"true"
                        }]
                }, 
                {
                 "id":20,
                 "objectgroup":
                    {
                     "draworder":"index",
                     "name":"",
                     "objects":[
                            {
                             "height":0,
                             "id":1,
                             "name":"",
                             "polygon":[
                                    {
                                     "x":0,
                                     "y":0
                                    }, 
                                    {
                                     "x":68.5455,
                                     "y":-0.181818
                                    }, 
                                    {
                                     "x":69.8182,
                                     "y":16.3636
                                    }, 
                                    {
                                     "x":46.1818,
                                     "y":55.0909
                                    }, 
                                    {
                                     "x":53.6364,
                                     "y":69.2727
                                    }, 
                                    {
                                     "x":0.181818,
                                     "y":69.2727
                                    }],
                             "rotation":0,
                             "type":"",
                             "visible":true,
                             "width":0,
                             "x":0,
                             "y":2.72727
                            }],
                     "opacity":1,
                     "type":"objectgroup",
                     "visible":true,
                     "x":0,
                     "y":0
                    },
                 "properties":[
                        {
                         "name":"collides",
                         "type":"string",
                         "value":"true"
                        }]
                }, 
                {
                 "id":22,
                 "objectgroup":
                    {
                     "draworder":"index",
                     "name":"",
                     "objects":[
                            {
                             "height":0,
                             "id":1,
                             "name":"",
                             "polygon":[
                                    {
                                     "x":0,
                                     "y":0
                                    }, 
                                    {
                                     "x":14.3636,
                                     "y":-37.0909
                                    }, 
                                    {
                                     "x":44.1818,
                                     "y":-49.6364
                                    }, 
                                    {
                                     "x":52,
                                     "y":-63.0909
                                    }, 
                                    {
                                     "x":61.4545,
                                     "y":-63.0909
                                    }, 
                                    {
                                     "x":61.6364,
                                     "y":0.909091
                                    }, 
                                    {
                                     "x":-0.181818,
                                     "y":1.45455
                                    }],
                             "rotation":0,
                             "type":"",
                             "visible":true,
                             "width":0,
                             "x":10.1818,
                             "y":70.7273
                            }],
                     "opacity":1,
                     "type":"objectgroup",
                     "visible":true,
                     "x":0,
                     "y":0
                    },
                 "properties":[
                        {
                         "name":"collides",
                         "type":"string",
                         "value":"true"
                        }]
                }, 
                {
                 "id":24,
                 "objectgroup":
                    {
                     "draworder":"index",
                     "name":"",
                     "objects":[
                            {
                             "height":0,
                             "id":1,
                             "name":"",
                             "polygon":[
                                    {
                                     "x":0.181818,
                                     "y":4
                                    }, 
                                    {
                                     "x":14.3636,
                                     "y":6.90909
                                    }, 
                                    {
                                     "x":21.0909,
                                     "y":23.8182
                                    }, 
                                    {
                                     "x":31.6364,
                                     "y":30
                                    }, 
                                    {
                                     "x":46.9091,
                                     "y":32.1818
                                    }, 
                                    {
                                     "x":50.7273,
                                     "y":51.2727
                                    }, 
                                    {
                                     "x":47.4545,
                                     "y":60.1818
                                    }, 
                                    {
                                     "x":52.3636,
                                     "y":71.2727
                                    }, 
                                    {
                                     "x":52.5455,
                                     "y":71.8182
                                    }, 
                                    {
                                     "x":0.363636,
                                     "y":72
                                    }],
                             "rotation":0,
                             "type":"",
                             "visible":true,
                             "width":0,
                             "x":-0.181818,
                             "y":0
                            }],
                     "opacity":1,
                     "type":"objectgroup",
                     "visible":true,
                     "x":0,
                     "y":0
                    },
                 "properties":[
                        {
                         "name":"collides",
                         "type":"string",
                         "value":"true"
                        }]
                }, 
                {
                 "id":35,
                 "objectgroup":
                    {
                     "draworder":"index",
                     "name":"",
                     "objects":[
                            {
                             "height":0,
                             "id":1,
                             "name":"",
                             "polygon":[
                                    {
                                     "x":0,
                                     "y":0
                                    }, 
                                    {
                                     "x":4.72727,
                                     "y":9.81818
                                    }, 
                                    {
                                     "x":0.363636,
                                     "y":16.9091
                                    }, 
                                    {
                                     "x":10.1818,
                                     "y":31.6364
                                    }, 
                                    {
                                     "x":2.18182,
                                     "y":45.0909
                                    }, 
                                    {
                                     "x":5.63636,
                                     "y":52.3636
                                    }, 
                                    {
                                     "x":-1.81818,
                                     "y":60.5455
                                    }, 
                                    {
                                     "x":1.45455,
                                     "y":72.3636
                                    }, 
                                    {
                                     "x":57.6364,
                                     "y":72.3636
                                    }, 
                                    {
                                     "x":57.6364,
                                     "y":0.727273
                                    }],
                             "rotation":0,
                             "type":"",
                             "visible":true,
                             "width":0,
                             "x":14.1818,
                             "y":-0.545455
                            }],
                     "opacity":1,
                     "type":"objectgroup",
                     "visible":true,
                     "x":0,
                     "y":0
                    },
                 "properties":[
                        {
                         "name":"collides",
                         "type":"string",
                         "value":"true"
                        }]
                }, 
                {
                 "id":36,
                 "objectgroup":
                    {
                     "draworder":"index",
                     "name":"",
                     "objects":[
                            {
                             "height":72,
                             "id":1,
                             "name":"",
                             "rotation":0,
                             "type":"",
                             "visible":true,
                             "width":72,
                             "x":0,
                             "y":0
                            }],
                     "opacity":1,
                     "type":"objectgroup",
                     "visible":true,
                     "x":0,
                     "y":0
                    },
                 "properties":[
                        {
                         "name":"collides",
                         "type":"string",
                         "value":"true"
                        }]
                }, 
                {
                 "id":37,
                 "objectgroup":
                    {
                     "draworder":"index",
                     "name":"",
                     "objects":[
                            {
                             "height":0,
                             "id":1,
                             "name":"",
                             "polygon":[
                                    {
                                     "x":0,
                                     "y":0
                                    }, 
                                    {
                                     "x":51.4545,
                                     "y":0.181818
                                    }, 
                                    {
                                     "x":57.6364,
                                     "y":13.0909
                                    }, 
                                    {
                                     "x":57.6364,
                                     "y":23.8182
                                    }, 
                                    {
                                     "x":64.9091,
                                     "y":33.8182
                                    }, 
                                    {
                                     "x":54.7273,
                                     "y":43.6364
                                    }, 
                                    {
                                     "x":44.7273,
                                     "y":58.3636
                                    }, 
                                    {
                                     "x":51.4545,
                                     "y":72.5455
                                    }, 
                                    {
                                     "x":0,
                                     "y":72.3636
                                    }],
                             "rotation":0,
                             "type":"",
                             "visible":true,
                             "width":0,
                             "x":0,
                             "y":-0.181818
                            }],
                     "opacity":1,
                     "type":"objectgroup",
                     "visible":true,
                     "x":0,
                     "y":0
                    },
                 "properties":[
                        {
                         "name":"collides",
                         "type":"string",
                         "value":"true"
                        }]
                }, 
                {
                 "id":39,
                 "objectgroup":
                    {
                     "draworder":"index",
                     "name":"",
                     "objects":[
                            {
                             "height":0,
                             "id":1,
                             "name":"",
                             "polygon":[
                                    {
                                     "x":0,
                                     "y":0
                                    }, 
                                    {
                                     "x":-14,
                                     "y":25.8182
                                    }, 
                                    {
                                     "x":-13.8182,
                                     "y":71.0909
                                    }, 
                                    {
                                     "x":58.1818,
                                     "y":71.2727
                                    }, 
                                    {
                                     "x":58.3636,
                                     "y":-0.545455
                                    }],
                             "rotation":0,
                             "type":"",
                             "visible":true,
                             "width":0,
                             "x":13.8182,
                             "y":0.363636
                            }],
                     "opacity":1,
                     "type":"objectgroup",
                     "visible":true,
                     "x":0,
                     "y":0
                    },
                 "properties":[
                        {
                         "name":"collides",
                         "type":"string",
                         "value":"true"
                        }]
                }, 
                {
                 "id":41,
                 "objectgroup":
                    {
                     "draworder":"index",
                     "name":"",
                     "objects":[
                            {
                             "height":0,
                             "id":1,
                             "name":"",
                             "polygon":[
                                    {
                                     "x":0,
                                     "y":0
                                    }, 
                                    {
                                     "x":22.9091,
                                     "y":23.4545
                                    }, 
                                    {
                                     "x":22.9091,
                                     "y":72.5455
                                    }, 
                                    {
                                     "x":-48.9091,
                                     "y":72.9091
                                    }, 
                                    {
                                     "x":-49.0909,
                                     "y":0.363636
                                    }],
                             "rotation":0,
                             "type":"",
                             "visible":true,
                             "width":0,
                             "x":48.9091,
                             "y":-0.545455
                            }],
                     "opacity":1,
                     "type":"objectgroup",
                     "visible":true,
                     "x":0,
                     "y":0
                    },
                 "properties":[
                        {
                         "name":"collides",
                         "type":"string",
                         "value":"true"
                        }]
                }],
         "tilewidth":72
        }],
 "tilewidth":72,
 "type":"map",
 "version":1.2,
 "width":30
}